django_spaceless_templates/__init__.py
django_spaceless_templates/mixins.py
django_spaceless_templates/utils.py
django_spaceless_templates/loaders/__init__.py
django_spaceless_templates/loaders/app_directories.py
django_spaceless_templates/loaders/filesystem.py
django_spaceless_templates-1.0.2.dist-info/LICENSE
django_spaceless_templates-1.0.2.dist-info/METADATA
django_spaceless_templates-1.0.2.dist-info/WHEEL
django_spaceless_templates-1.0.2.dist-info/top_level.txt
django_spaceless_templates-1.0.2.dist-info/RECORD
