Metadata-Version: 2.1
Name: django-spaceless-templates
Version: 1.0.2
Summary: Simple Django template loader that minifies html output.
Home-page: https://github.com/martinsvoboda/django-spaceless-templates
Author: Martin Svoboda
Author-email: martin.svoboda@gmail.com
License: MIT License
Keywords: django,template,minification,html,minifier
Platform: UNKNOWN
Classifier: Environment :: Web Environment
Classifier: Framework :: Django
Classifier: Intended Audience :: Developers
Classifier: License :: OSI Approved :: MIT License
Classifier: Operating System :: OS Independent
Classifier: Programming Language :: Python
Classifier: Programming Language :: Python :: 3.5
Classifier: Topic :: Internet :: WWW/HTTP
Classifier: Topic :: Internet :: WWW/HTTP :: Dynamic Content
License-File: LICENSE
Requires-Dist: Django (>=1.8)
